{
  "auth": {
    "othia74325d1e": {
      "service": "Cognito",
      "providerPlugin": "awscloudformation",
      "dependsOn": [],
      "customAuth": false,
      "frontendAuthConfig": {
        "socialProviders": [],
        "usernameAttributes": [
          "PHONE_NUMBER"
        ],
        "signupAttributes": [
          "EMAIL"
        ],
        "passwordProtectionSettings": {
          "passwordPolicyMinLength": 8,
          "passwordPolicyCharacters": []
        },
        "mfaConfiguration": "OFF",
        "mfaTypes": [
          "SMS"
        ],
        "verificationMechanisms": [
          "EMAIL"
        ]
      }
    }
  },
  "function": {
    "apiLambda": {
      "build": true,
      "providerPlugin": "awscloudformation",
      "service": "Lambda"
    },
    "getFavouriteEventsAndActivities": {
      "build": true,
      "providerPlugin": "awscloudformation",
      "service": "Lambda",
      "dependsOn": []
    },
    "removeFavourite": {
      "build": true,
      "providerPlugin": "awscloudformation",
      "service": "Lambda"
    },
    "getEAIdsForCategory": {
      "build": true,
      "providerPlugin": "awscloudformation",
      "service": "Lambda"
    },
    "getEASummary": {
      "build": true,
      "providerPlugin": "awscloudformation",
      "service": "Lambda"
    },
    "getEAIdsForEventSeries": {
      "build": true,
      "providerPlugin": "awscloudformation",
      "service": "Lambda"
    },
    "getEAIdsForLocation": {
      "build": true,
      "providerPlugin": "awscloudformation",
      "service": "Lambda"
    },
    "getSearchResultIds": {
      "build": true,
      "providerPlugin": "awscloudformation",
      "service": "Lambda"
    },
    "getUserInterests": {
      "build": true,
      "providerPlugin": "awscloudformation",
      "service": "Lambda"
    },
    "getHostedEA": {
      "build": true,
      "providerPlugin": "awscloudformation",
      "service": "Lambda"
    },
    "getUserInfo": {
      "build": true,
      "providerPlugin": "awscloudformation",
      "service": "Lambda"
    },
    "addLikedEA": {
      "build": true,
      "providerPlugin": "awscloudformation",
      "service": "Lambda"
    },
    "isEALikedByUser": {
      "build": true,
      "providerPlugin": "awscloudformation",
      "service": "Lambda"
    },
    "getHomePageIds": {
      "build": true,
      "providerPlugin": "awscloudformation",
      "service": "Lambda"
    },
    "getMapResultIds": {
      "build": true,
      "providerPlugin": "awscloudformation",
      "service": "Lambda"
    },
    "deleteAccount": {
      "build": true,
      "providerPlugin": "awscloudformation",
      "service": "Lambda"
    },
    "savePrivateUserInformation": {
      "build": true,
      "providerPlugin": "awscloudformation",
      "service": "Lambda"
    },
    "deleteEA": {
      "build": true,
      "providerPlugin": "awscloudformation",
      "service": "Lambda"
    },
    "createEA": {
      "build": true,
      "providerPlugin": "awscloudformation",
      "service": "Lambda"
    },
    "getPublicUserInfo": {
      "build": true,
      "providerPlugin": "awscloudformation",
      "service": "Lambda"
    }
  },
  "api": {
    "othiaApi": {
      "service": "API Gateway",
      "providerPlugin": "awscloudformation",
      "dependsOn": [
        {
          "category": "function",
          "resourceName": "apiLambda",
          "attributes": [
            "Name",
            "Arn"
          ]
        }
      ]
    }
  }
}